my_own_package/__init__.py
first_package_Nada-0.2.0.dist-info/METADATA
first_package_Nada-0.2.0.dist-info/WHEEL
first_package_Nada-0.2.0.dist-info/top_level.txt
first_package_Nada-0.2.0.dist-info/RECORD
