Metadata-Version: 2.1
Name: first-package-Nada
Version: 0.2.0
Summary: my first package
Author: Nada
Author-email: nada_fhn24@gmail.com
